[{"transactionDate":"103.02.20","produceNumber":"73","produceName":"\u5c0f\u756a\u8304-\u5b0c\u5973","marketNumber":"338","marketName":"\u6843\u5712\u7e23","topPrice":"10","middlePrice":"9","lowPrice":"7","averagePrice":"9","transactionAmount":"106","number":"73","main_category":"fruit","sub_category":""},{"transactionDate":"103.02.20","produceNumber":"P3","produceName":"\u756a\u77f3\u69b4-\u5e1d\u738b\u82ad","marketNumber":"338","marketName":"\u6843\u5712\u7e23","topPrice":"15","middlePrice":"10.8","lowPrice":"8","averagePrice":"10.8","transactionAmount":"288","number":"P3","main_category":"fruit","sub_category":""},{"transactionDate":"103.02.20","produceNumber":"31","produceName":"\u91cb\u8fe6","marketNumber":"338","marketName":"\u6843\u5712\u7e23","topPrice":"12","middlePrice":"12","lowPrice":"12","averagePrice":"12","transactionAmount":"38","number":"31","main_category":"fruit","sub_category":""},{"transactionDate":"103.02.20","produceNumber":"71","produceName":"\u5c0f\u756a\u8304-\u4e00\u822c","marketNumber":"338","marketName":"\u6843\u5712\u7e23","topPrice":"12","middlePrice":"12","lowPrice":"12","averagePrice":"12","transactionAmount":"12","number":"71","main_category":"fruit","sub_category":""},{"transactionDate":"103.02.20","produceNumber":"70","produceName":"\u5c0f\u756a\u8304-\u5176\u4ed6","marketNumber":"338","marketName":"\u6843\u5712\u7e23","topPrice":"15","middlePrice":"15","lowPrice":"15","averagePrice":"15","transactionAmount":"60","number":"70","main_category":"fruit","sub_category":""},{"transactionDate":"103.02.20","produceNumber":"P0","produceName":"\u756a\u77f3\u69b4-\u5176\u4ed6","marketNumber":"338","marketName":"\u6843\u5712\u7e23","topPrice":"15","middlePrice":"15","lowPrice":"15","averagePrice":"15","transactionAmount":"20","number":"P0","main_category":"fruit","sub_category":""},{"transactionDate":"103.02.20","produceNumber":"P1","produceName":"\u756a\u77f3\u69b4-\u73cd\u73e0\u82ad","marketNumber":"338","marketName":"\u6843\u5712\u7e23","topPrice":"18","middlePrice":"16.4","lowPrice":"15","averagePrice":"16.4","transactionAmount":"198","number":"P1","main_category":"fruit","sub_category":""},{"transactionDate":"103.02.20","produceNumber":"72","produceName":"\u5c0f\u756a\u8304-\u8056\u5973","marketNumber":"338","marketName":"\u6843\u5712\u7e23","topPrice":"70","middlePrice":"24.4","lowPrice":"10","averagePrice":"24.4","transactionAmount":"122","number":"72","main_category":"fruit","sub_category":""},{"transactionDate":"103.02.20","produceNumber":"32","produceName":"\u91cb\u8fe6-\u9cf3\u68a8\u91cb\u8fe6","marketNumber":"338","marketName":"\u6843\u5712\u7e23","topPrice":"35","middlePrice":"30","lowPrice":"25","averagePrice":"30","transactionAmount":"68","number":"32","main_category":"fruit","sub_category":""}]