[{"transactionDate":"102.05.21","produceNumber":"T7","produceName":"\u897f\u74dc-\u79c0\u9234","marketNumber":"400","marketName":"\u53f0\u4e2d\u5e02\u5834","topPrice":"7.8","middlePrice":"6.2","lowPrice":"5","averagePrice":"6.2","transactionAmount":"1594","number":"T7","main_category":"fruit","sub_category":""},{"transactionDate":"102.05.21","produceNumber":"61","produceName":"\u7518\u8517-\u5e36\u76ae","marketNumber":"400","marketName":"\u53f0\u4e2d\u5e02\u5834","topPrice":"10","middlePrice":"7.3","lowPrice":"6","averagePrice":"7.6","transactionAmount":"6126","number":"61","main_category":"fruit","sub_category":""},{"transactionDate":"102.05.21","produceNumber":"11","produceName":"\u6930\u5b50","marketNumber":"400","marketName":"\u53f0\u4e2d\u5e02\u5834","topPrice":"10.7","middlePrice":"8.5","lowPrice":"7","averagePrice":"9.7","transactionAmount":"14901","number":"11","main_category":"fruit","sub_category":""},{"transactionDate":"102.05.21","produceNumber":"T6","produceName":"\u897f\u74dc-\u7d05\u8089","marketNumber":"400","marketName":"\u53f0\u4e2d\u5e02\u5834","topPrice":"12.3","middlePrice":"9.8","lowPrice":"6","averagePrice":"9.7","transactionAmount":"18850","number":"T6","main_category":"fruit","sub_category":""},{"transactionDate":"102.05.21","produceNumber":"T1","produceName":"\u897f\u74dc-\u5927\u897f\u74dc","marketNumber":"400","marketName":"\u53f0\u4e2d\u5e02\u5834","topPrice":"18.5","middlePrice":"10.5","lowPrice":"8","averagePrice":"10.6","transactionAmount":"88942","number":"T1","main_category":"fruit","sub_category":""},{"transactionDate":"102.05.21","produceNumber":"T5","produceName":"\u897f\u74dc-\u9ec3\u8089","marketNumber":"400","marketName":"\u53f0\u4e2d\u5e02\u5834","topPrice":"13.2","middlePrice":"10.2","lowPrice":"8","averagePrice":"10.6","transactionAmount":"39002","number":"T5","main_category":"fruit","sub_category":""},{"transactionDate":"102.05.21","produceNumber":"T4","produceName":"\u897f\u74dc-\u9cf3\u5149\u3001\u82f1\u5999","marketNumber":"400","marketName":"\u53f0\u4e2d\u5e02\u5834","topPrice":"13","middlePrice":"11.5","lowPrice":"10","averagePrice":"11.3","transactionAmount":"2761","number":"T4","main_category":"fruit","sub_category":""},{"transactionDate":"102.05.21","produceNumber":"Y0","produceName":"\u6843\u5b50-\u5176\u4ed6","marketNumber":"400","marketName":"\u53f0\u4e2d\u5e02\u5834","topPrice":"13","middlePrice":"13","lowPrice":"13","averagePrice":"13","transactionAmount":"32","number":"Y0","main_category":"fruit","sub_category":""},{"transactionDate":"102.05.21","produceNumber":"G9","produceName":"\u6ce2\u7f85\u871c","marketNumber":"400","marketName":"\u53f0\u4e2d\u5e02\u5834","topPrice":"15","middlePrice":"15","lowPrice":"10","averagePrice":"14.4","transactionAmount":"152","number":"G9","main_category":"fruit","sub_category":""},{"transactionDate":"102.05.21","produceNumber":"R8","produceName":"\u8292\u679c-\u8292\u679c\u9752","marketNumber":"400","marketName":"\u53f0\u4e2d\u5e02\u5834","topPrice":"17","middlePrice":"12.9","lowPrice":"9.3","averagePrice":"14.4","transactionAmount":"854","number":"R8","main_category":"fruit","sub_category":""},{"transactionDate":"102.05.21","produceNumber":"H4","produceName":"\u8461\u8404\u67da-\u7d05\u8089","marketNumber":"400","marketName":"\u53f0\u4e2d\u5e02\u5834","topPrice":"20","middlePrice":"15","lowPrice":"15","averagePrice":"15.4","transactionAmount":"992","number":"H4","main_category":"fruit","sub_category":""},{"transactionDate":"102.05.21","produceNumber":"M3","produceName":"\u694a\u6843-\u99ac\u4f86\u4e9e\u7a2e","marketNumber":"400","marketName":"\u53f0\u4e2d\u5e02\u5834","topPrice":"16","middlePrice":"16","lowPrice":"16","averagePrice":"16","transactionAmount":"15","number":"M3","main_category":"fruit","sub_category":""},{"transactionDate":"102.05.21","produceNumber":"A0","produceName":"\u9999\u8549-\u5176\u4ed6","marketNumber":"400","marketName":"\u53f0\u4e2d\u5e02\u5834","topPrice":"18","middlePrice":"17.5","lowPrice":"17","averagePrice":"17.3","transactionAmount":"45","number":"A0","main_category":"fruit","sub_category":""},{"transactionDate":"102.05.21","produceNumber":"P2","produceName":"\u756a\u77f3\u69b4-\u7d05\u5fc3","marketNumber":"400","marketName":"\u53f0\u4e2d\u5e02\u5834","topPrice":"32.5","middlePrice":"20.5","lowPrice":"13","averagePrice":"18.2","transactionAmount":"331","number":"P2","main_category":"fruit","sub_category":""},{"transactionDate":"102.05.21","produceNumber":"B2","produceName":"\u9cf3\u68a8-\u91d1\u947d\u9cf3\u68a8","marketNumber":"400","marketName":"\u53f0\u4e2d\u5e02\u5834","topPrice":"29","middlePrice":"20","lowPrice":"13.9","averagePrice":"19","transactionAmount":"135135","number":"B2","main_category":"fruit","sub_category":""},{"transactionDate":"102.05.21","produceNumber":"B6","produceName":"\u9cf3\u68a8-\u751c\u871c\u871c","marketNumber":"400","marketName":"\u53f0\u4e2d\u5e02\u5834","topPrice":"23","middlePrice":"19","lowPrice":"16","averagePrice":"19.7","transactionAmount":"4620","number":"B6","main_category":"fruit","sub_category":""},{"transactionDate":"102.05.21","produceNumber":"E1","produceName":"\u751c\u6a59-\u67f3\u6a59","marketNumber":"400","marketName":"\u53f0\u4e2d\u5e02\u5834","topPrice":"24","middlePrice":"24","lowPrice":"17.5","averagePrice":"19.4","transactionAmount":"3214","number":"E1","main_category":"fruit","sub_category":""},{"transactionDate":"102.05.21","produceNumber":"N0","produceName":"\u674e-\u5176\u4ed6","marketNumber":"400","marketName":"\u53f0\u4e2d\u5e02\u5834","topPrice":"20","middlePrice":"20","lowPrice":"20","averagePrice":"20","transactionAmount":"30","number":"N0","main_category":"fruit","sub_category":""},{"transactionDate":"102.05.21","produceNumber":"F4","produceName":"\u96dc\u67d1-\u6854\u5b50","marketNumber":"400","marketName":"\u53f0\u4e2d\u5e02\u5834","topPrice":"26.7","middlePrice":"21.9","lowPrice":"16.7","averagePrice":"23.4","transactionAmount":"803","number":"F4","main_category":"fruit","sub_category":""},{"transactionDate":"102.05.21","produceNumber":"P5","produceName":"\u756a\u77f3\u69b4-\u6c34\u6676\u7121\u4ed4","marketNumber":"400","marketName":"\u53f0\u4e2d\u5e02\u5834","topPrice":"28","middlePrice":"25.3","lowPrice":"20","averagePrice":"24.4","transactionAmount":"132","number":"P5","main_category":"fruit","sub_category":""},{"transactionDate":"102.05.21","produceNumber":"91","produceName":"\u5176\u4ed6","marketNumber":"400","marketName":"\u53f0\u4e2d\u5e02\u5834","topPrice":"128.7","middlePrice":"51.4","lowPrice":"19","averagePrice":"25.5","transactionAmount":"4819","number":"91","main_category":"fruit","sub_category":""},{"transactionDate":"102.05.21","produceNumber":"A2","produceName":"\u9999\u8549-\u82ad\u8549","marketNumber":"400","marketName":"\u53f0\u4e2d\u5e02\u5834","topPrice":"30.8","middlePrice":"26.3","lowPrice":"20.2","averagePrice":"25.4","transactionAmount":"5253","number":"A2","main_category":"fruit","sub_category":""},{"transactionDate":"102.05.21","produceNumber":"N4","produceName":"\u674e-\u9ec3\u8089\u674e","marketNumber":"400","marketName":"\u53f0\u4e2d\u5e02\u5834","topPrice":"30","middlePrice":"25","lowPrice":"20","averagePrice":"26.6","transactionAmount":"752","number":"N4","main_category":"fruit","sub_category":""},{"transactionDate":"102.05.21","produceNumber":"P1","produceName":"\u756a\u77f3\u69b4-\u73cd\u73e0\u82ad","marketNumber":"400","marketName":"\u53f0\u4e2d\u5e02\u5834","topPrice":"35.5","middlePrice":"26.3","lowPrice":"17.7","averagePrice":"26.9","transactionAmount":"26100","number":"P1","main_category":"fruit","sub_category":""},{"transactionDate":"102.05.21","produceNumber":"I1","produceName":"\u6728\u74dc-\u7db2\u5ba4\u7d05\u8089","marketNumber":"400","marketName":"\u53f0\u4e2d\u5e02\u5834","topPrice":"34.1","middlePrice":"28.4","lowPrice":"22","averagePrice":"27.5","transactionAmount":"37398","number":"I1","main_category":"fruit","sub_category":""},{"transactionDate":"102.05.21","produceNumber":"P3","produceName":"\u756a\u77f3\u69b4-\u5e1d\u738b\u82ad","marketNumber":"400","marketName":"\u53f0\u4e2d\u5e02\u5834","topPrice":"40","middlePrice":"33.7","lowPrice":"16.5","averagePrice":"27.8","transactionAmount":"488","number":"P3","main_category":"fruit","sub_category":""},{"transactionDate":"102.05.21","produceNumber":"72","produceName":"\u5c0f\u756a\u8304-\u8056\u5973","marketNumber":"400","marketName":"\u53f0\u4e2d\u5e02\u5834","topPrice":"108","middlePrice":"31.1","lowPrice":"19","averagePrice":"28.8","transactionAmount":"11890","number":"72","main_category":"fruit","sub_category":""},{"transactionDate":"102.05.21","produceNumber":"F1","produceName":"\u6ab8\u6aac-\u6ab8\u6aac","marketNumber":"400","marketName":"\u53f0\u4e2d\u5e02\u5834","topPrice":"34.2","middlePrice":"28.1","lowPrice":"22.2","averagePrice":"28.2","transactionAmount":"3154","number":"F1","main_category":"fruit","sub_category":""},{"transactionDate":"102.05.21","produceNumber":"W6","produceName":"\u6d0b\u9999\u74dc-\u5149\u9762\u7da0\u8089","marketNumber":"400","marketName":"\u53f0\u4e2d\u5e02\u5834","topPrice":"37.5","middlePrice":"30","lowPrice":"22.5","averagePrice":"29.7","transactionAmount":"4688","number":"W6","main_category":"fruit","sub_category":""},{"transactionDate":"102.05.21","produceNumber":"N2","produceName":"\u674e-\u6843\u63a5\u674e","marketNumber":"400","marketName":"\u53f0\u4e2d\u5e02\u5834","topPrice":"33.5","middlePrice":"28.4","lowPrice":"20","averagePrice":"30.8","transactionAmount":"1410","number":"N2","main_category":"fruit","sub_category":""},{"transactionDate":"102.05.21","produceNumber":"V1","produceName":"\u751c\u74dc-\u7f8e\u6fc3","marketNumber":"400","marketName":"\u53f0\u4e2d\u5e02\u5834","topPrice":"52.8","middlePrice":"30.9","lowPrice":"15.1","averagePrice":"30.3","transactionAmount":"22811","number":"V1","main_category":"fruit","sub_category":""},{"transactionDate":"102.05.21","produceNumber":"70","produceName":"\u5c0f\u756a\u8304-\u5176\u4ed6","marketNumber":"400","marketName":"\u53f0\u4e2d\u5e02\u5834","topPrice":"41","middlePrice":"33.3","lowPrice":"25","averagePrice":"31.8","transactionAmount":"332","number":"70","main_category":"fruit","sub_category":""},{"transactionDate":"102.05.21","produceNumber":"A1","produceName":"\u9999\u8549","marketNumber":"400","marketName":"\u53f0\u4e2d\u5e02\u5834","topPrice":"35.7","middlePrice":"29.8","lowPrice":"22.8","averagePrice":"31.2","transactionAmount":"41311","number":"A1","main_category":"fruit","sub_category":""},{"transactionDate":"102.05.21","produceNumber":"B0","produceName":"\u9cf3\u68a8-\u5176\u4ed6","marketNumber":"400","marketName":"\u53f0\u4e2d\u5e02\u5834","topPrice":"38","middlePrice":"34.5","lowPrice":"26","averagePrice":"33","transactionAmount":"329","number":"B0","main_category":"fruit","sub_category":""},{"transactionDate":"102.05.21","produceNumber":"F5","produceName":"\u96dc\u67d1-\u7121\u5b50\u6ab8\u6aac","marketNumber":"400","marketName":"\u53f0\u4e2d\u5e02\u5834","topPrice":"41","middlePrice":"34.8","lowPrice":"25.8","averagePrice":"35.1","transactionAmount":"700","number":"F5","main_category":"fruit","sub_category":""},{"transactionDate":"102.05.21","produceNumber":"R5","produceName":"\u8292\u679c-\u9ed1\u9999\u91d1\u8208","marketNumber":"400","marketName":"\u53f0\u4e2d\u5e02\u5834","topPrice":"35","middlePrice":"35","lowPrice":"35","averagePrice":"35","transactionAmount":"7","number":"R5","main_category":"fruit","sub_category":""},{"transactionDate":"102.05.21","produceNumber":"Y5","produceName":"\u6843\u5b50-\u798f\u58fd\u6843","marketNumber":"400","marketName":"\u53f0\u4e2d\u5e02\u5834","topPrice":"35","middlePrice":"35","lowPrice":"35","averagePrice":"35","transactionAmount":"575","number":"Y5","main_category":"fruit","sub_category":""},{"transactionDate":"102.05.21","produceNumber":"Q1","produceName":"\u84ee\u9727-\u7d05\u84ee\u9727","marketNumber":"400","marketName":"\u53f0\u4e2d\u5e02\u5834","topPrice":"53.5","middlePrice":"34.4","lowPrice":"17.7","averagePrice":"37.5","transactionAmount":"19557","number":"Q1","main_category":"fruit","sub_category":""},{"transactionDate":"102.05.21","produceNumber":"W1","produceName":"\u6d0b\u9999\u74dc-\u7db2\u72c0\u7d05\u8089","marketNumber":"400","marketName":"\u53f0\u4e2d\u5e02\u5834","topPrice":"57.5","middlePrice":"36.2","lowPrice":"12.3","averagePrice":"37","transactionAmount":"10753","number":"W1","main_category":"fruit","sub_category":""},{"transactionDate":"102.05.21","produceNumber":"W2","produceName":"\u6d0b\u9999\u74dc-\u7db2\u72c0\u7da0\u8089","marketNumber":"400","marketName":"\u53f0\u4e2d\u5e02\u5834","topPrice":"55.8","middlePrice":"31","lowPrice":"9.7","averagePrice":"37.4","transactionAmount":"11928","number":"W2","main_category":"fruit","sub_category":""},{"transactionDate":"102.05.21","produceNumber":"Y3","produceName":"\u6843\u5b50-\u751c\u6843","marketNumber":"400","marketName":"\u53f0\u4e2d\u5e02\u5834","topPrice":"68.8","middlePrice":"45.6","lowPrice":"22.8","averagePrice":"37.5","transactionAmount":"4068","number":"Y3","main_category":"fruit","sub_category":""},{"transactionDate":"102.05.21","produceNumber":"Q2","produceName":"\u84ee\u9727-\u5b50\u5f48\u578b","marketNumber":"400","marketName":"\u53f0\u4e2d\u5e02\u5834","topPrice":"51.7","middlePrice":"34.1","lowPrice":"27","averagePrice":"38.3","transactionAmount":"621","number":"Q2","main_category":"fruit","sub_category":""},{"transactionDate":"102.05.21","produceNumber":"R0","produceName":"\u8292\u679c-\u5176\u4ed6","marketNumber":"400","marketName":"\u53f0\u4e2d\u5e02\u5834","topPrice":"42","middlePrice":"40","lowPrice":"40","averagePrice":"41.3","transactionAmount":"192","number":"R0","main_category":"fruit","sub_category":""},{"transactionDate":"102.05.21","produceNumber":"R6","produceName":"\u8292\u679c-\u91d1\u714c","marketNumber":"400","marketName":"\u53f0\u4e2d\u5e02\u5834","topPrice":"51.9","middlePrice":"37","lowPrice":"25","averagePrice":"42.9","transactionAmount":"6069","number":"R6","main_category":"fruit","sub_category":""},{"transactionDate":"102.05.21","produceNumber":"R3","produceName":"\u8292\u679c-\u672c\u5cf6","marketNumber":"400","marketName":"\u53f0\u4e2d\u5e02\u5834","topPrice":"59.4","middlePrice":"42","lowPrice":"26.1","averagePrice":"44","transactionAmount":"3320","number":"R3","main_category":"fruit","sub_category":""},{"transactionDate":"102.05.21","produceNumber":"N3","produceName":"\u674e-\u7d05\u8089\u674e","marketNumber":"400","marketName":"\u53f0\u4e2d\u5e02\u5834","topPrice":"58","middlePrice":"42.5","lowPrice":"35","averagePrice":"45.8","transactionAmount":"4621","number":"N3","main_category":"fruit","sub_category":""},{"transactionDate":"102.05.21","produceNumber":"I3","produceName":"\u6728\u74dc-\u65e5\u6607\u7a2e","marketNumber":"400","marketName":"\u53f0\u4e2d\u5e02\u5834","topPrice":"54","middlePrice":"40.8","lowPrice":"25","averagePrice":"47.5","transactionAmount":"330","number":"I3","main_category":"fruit","sub_category":""},{"transactionDate":"102.05.21","produceNumber":"J0","produceName":"\u8354\u679d-\u5176\u4ed6","marketNumber":"400","marketName":"\u53f0\u4e2d\u5e02\u5834","topPrice":"60","middlePrice":"48.3","lowPrice":"40","averagePrice":"49.3","transactionAmount":"6335","number":"J0","main_category":"fruit","sub_category":""},{"transactionDate":"102.05.21","produceNumber":"H49","produceName":"\u8461\u8404\u67da-\u9032\u53e3\u7d05\u8089","marketNumber":"400","marketName":"\u53f0\u4e2d\u5e02\u5834","topPrice":"55","middlePrice":"52.5","lowPrice":"50","averagePrice":"50.2","transactionAmount":"650","number":"H49","main_category":"fruit","sub_category":""},{"transactionDate":"102.05.21","produceNumber":"R2","produceName":"\u8292\u679c-\u7d05\u9f8d\u7389\u6587","marketNumber":"400","marketName":"\u53f0\u4e2d\u5e02\u5834","topPrice":"65","middlePrice":"47.5","lowPrice":"27.5","averagePrice":"51.6","transactionAmount":"150","number":"R2","main_category":"fruit","sub_category":""},{"transactionDate":"102.05.21","produceNumber":"O2","produceName":"\u68a8-\u79cb\u6c34\u68a8","marketNumber":"400","marketName":"\u53f0\u4e2d\u5e02\u5834","topPrice":"77","middlePrice":"51.7","lowPrice":"30.2","averagePrice":"52.2","transactionAmount":"28800","number":"O2","main_category":"fruit","sub_category":""},{"transactionDate":"102.05.21","produceNumber":"A3","produceName":"\u9999\u8549-\u65e6\u8549","marketNumber":"400","marketName":"\u53f0\u4e2d\u5e02\u5834","topPrice":"62.5","middlePrice":"50.2","lowPrice":"43.5","averagePrice":"54.8","transactionAmount":"819","number":"A3","main_category":"fruit","sub_category":""},{"transactionDate":"102.05.21","produceNumber":"E9","produceName":"\u751c\u6a59-\u9032\u53e3","marketNumber":"400","marketName":"\u53f0\u4e2d\u5e02\u5834","topPrice":"80","middlePrice":"67.1","lowPrice":"50","averagePrice":"54.1","transactionAmount":"2680","number":"E9","main_category":"fruit","sub_category":""},{"transactionDate":"102.05.21","produceNumber":"J2","produceName":"\u8354\u679d-\u9ed1\u8449","marketNumber":"400","marketName":"\u53f0\u4e2d\u5e02\u5834","topPrice":"60","middlePrice":"60","lowPrice":"60","averagePrice":"60","transactionAmount":"126","number":"J2","main_category":"fruit","sub_category":""},{"transactionDate":"102.05.21","produceNumber":"51","produceName":"\u767e\u9999\u679c-\u6539\u826f\u7a2e","marketNumber":"400","marketName":"\u53f0\u4e2d\u5e02\u5834","topPrice":"80","middlePrice":"61.7","lowPrice":"40","averagePrice":"61.3","transactionAmount":"120","number":"51","main_category":"fruit","sub_category":""},{"transactionDate":"102.05.21","produceNumber":"R1","produceName":"\u8292\u679c-\u611b\u6587","marketNumber":"400","marketName":"\u53f0\u4e2d\u5e02\u5834","topPrice":"91.5","middlePrice":"53.9","lowPrice":"32.2","averagePrice":"61.7","transactionAmount":"31336","number":"R1","main_category":"fruit","sub_category":""},{"transactionDate":"102.05.21","produceNumber":"S1","produceName":"\u8461\u8404-\u5de8\u5cf0","marketNumber":"400","marketName":"\u53f0\u4e2d\u5e02\u5834","topPrice":"130.6","middlePrice":"67.8","lowPrice":"41.2","averagePrice":"63.8","transactionAmount":"14543","number":"S1","main_category":"fruit","sub_category":""},{"transactionDate":"102.05.21","produceNumber":"O5","produceName":"\u68a8-\u8c50\u6c34\u68a8","marketNumber":"400","marketName":"\u53f0\u4e2d\u5e02\u5834","topPrice":"92.5","middlePrice":"65","lowPrice":"45","averagePrice":"66.4","transactionAmount":"1050","number":"O5","main_category":"fruit","sub_category":""},{"transactionDate":"102.05.21","produceNumber":"O9","produceName":"\u68a8-\u9032\u53e3","marketNumber":"400","marketName":"\u53f0\u4e2d\u5e02\u5834","topPrice":"80","middlePrice":"80","lowPrice":"80","averagePrice":"80","transactionAmount":"80","number":"O9","main_category":"fruit","sub_category":""},{"transactionDate":"102.05.21","produceNumber":"919","produceName":"\u5176\u4ed6-\u9032\u53e3","marketNumber":"400","marketName":"\u53f0\u4e2d\u5e02\u5834","topPrice":"110","middlePrice":"105","lowPrice":"55","averagePrice":"86.4","transactionAmount":"55","number":"919","main_category":"fruit","sub_category":""},{"transactionDate":"102.05.21","produceNumber":"J1","produceName":"\u8354\u679d-\u7389\u8377\u5305","marketNumber":"400","marketName":"\u53f0\u4e2d\u5e02\u5834","topPrice":"107.2","middlePrice":"94.9","lowPrice":"80.9","averagePrice":"92.1","transactionAmount":"16339","number":"J1","main_category":"fruit","sub_category":""},{"transactionDate":"102.05.21","produceNumber":"X69","produceName":"\u860b\u679c-\u5bcc\u58eb(\u9032\u53e3)","marketNumber":"400","marketName":"\u53f0\u4e2d\u5e02\u5834","topPrice":"124.1","middlePrice":"100","lowPrice":"77.3","averagePrice":"96.3","transactionAmount":"19349","number":"X69","main_category":"fruit","sub_category":""},{"transactionDate":"102.05.21","produceNumber":"Y39","produceName":"\u751c\u6843-\u751c\u6843\u9032\u53e3","marketNumber":"400","marketName":"\u53f0\u4e2d\u5e02\u5834","topPrice":"100","middlePrice":"100","lowPrice":"100","averagePrice":"100","transactionAmount":"1160","number":"Y39","main_category":"fruit","sub_category":""},{"transactionDate":"102.05.21","produceNumber":"74","produceName":"\u5c0f\u756a\u8304-\u7389\u5973","marketNumber":"400","marketName":"\u53f0\u4e2d\u5e02\u5834","topPrice":"155","middlePrice":"129.3","lowPrice":"60","averagePrice":"110.8","transactionAmount":"698","number":"74","main_category":"fruit","sub_category":""},{"transactionDate":"102.05.21","produceNumber":"G49","produceName":"\u5947\u7570\u679c-\u9032\u53e3","marketNumber":"400","marketName":"\u53f0\u4e2d\u5e02\u5834","topPrice":"130","middlePrice":"111.7","lowPrice":"100","averagePrice":"112.7","transactionAmount":"6643","number":"G49","main_category":"fruit","sub_category":""},{"transactionDate":"102.05.21","produceNumber":"S9","produceName":"\u8461\u8404-\u9032\u53e3","marketNumber":"400","marketName":"\u53f0\u4e2d\u5e02\u5834","topPrice":"125","middlePrice":"118.1","lowPrice":"96.7","averagePrice":"116.4","transactionAmount":"7225","number":"S9","main_category":"fruit","sub_category":""},{"transactionDate":"102.05.21","produceNumber":"859","produceName":"\u69b4\u69e4-\u9032\u53e3","marketNumber":"400","marketName":"\u53f0\u4e2d\u5e02\u5834","topPrice":"125","middlePrice":"120","lowPrice":"120","averagePrice":"123.7","transactionAmount":"186","number":"859","main_category":"fruit","sub_category":""},{"transactionDate":"102.05.21","produceNumber":"812","produceName":"\u706b\u9f8d\u679c-\u7d05\u8089","marketNumber":"400","marketName":"\u53f0\u4e2d\u5e02\u5834","topPrice":"160","middlePrice":"130","lowPrice":"100","averagePrice":"130","transactionAmount":"90","number":"812","main_category":"fruit","sub_category":""},{"transactionDate":"102.05.21","produceNumber":"C9","produceName":"\u692a\u67d1-\u9032\u53e3","marketNumber":"400","marketName":"\u53f0\u4e2d\u5e02\u5834","topPrice":"140","middlePrice":"140","lowPrice":"100","averagePrice":"132.9","transactionAmount":"51","number":"C9","main_category":"fruit","sub_category":""},{"transactionDate":"102.05.21","produceNumber":"Y9","produceName":"\u6843\u5b50-\u9032\u53e3","marketNumber":"400","marketName":"\u53f0\u4e2d\u5e02\u5834","topPrice":"200","middlePrice":"147.5","lowPrice":"125","averagePrice":"142.3","transactionAmount":"1075","number":"Y9","main_category":"fruit","sub_category":""},{"transactionDate":"102.05.21","produceNumber":"469","produceName":"\u85cd\u8393-\u9032\u53e3\u85cd\u8393","marketNumber":"400","marketName":"\u53f0\u4e2d\u5e02\u5834","topPrice":"250","middlePrice":"250","lowPrice":"205","averagePrice":"231.5","transactionAmount":"631","number":"469","main_category":"fruit","sub_category":""},{"transactionDate":"102.05.21","produceNumber":"839","produceName":"\u6afb\u6843-\u9032\u53e3","marketNumber":"400","marketName":"\u53f0\u4e2d\u5e02\u5834","topPrice":"500","middlePrice":"500","lowPrice":"500","averagePrice":"500","transactionAmount":"361","number":"839","main_category":"fruit","sub_category":""}]